bmi_roms/__init__.py
bmi_roms/_version.py
bmi_roms/bmi.py
bmi_roms/errors.py
bmi_roms/utils.py
bmi_roms-0.1.0.dist-info/LICENSE.txt
bmi_roms-0.1.0.dist-info/METADATA
bmi_roms-0.1.0.dist-info/WHEEL
bmi_roms-0.1.0.dist-info/top_level.txt
bmi_roms-0.1.0.dist-info/RECORD
