Metadata-Version: 2.1
Name: bmi-roms
Version: 0.1.0
Summary: BMI implementation for ROMS model data https://www.myroms.org/
Home-page: http://csdms.colorado.edu
Author: Tian Gan
Author-email: jamy127@foxmail.com
License-File: LICENSE.txt
Requires-Dist: bmipy
Requires-Dist: netcdf4
Requires-Dist: numpy
Requires-Dist: pyyaml
Requires-Dist: requests
Requires-Dist: xarray
